uzpreprocessor/__init__.py
uzpreprocessor/date.py
uzpreprocessor/datetime.py
uzpreprocessor/math.py
uzpreprocessor/number.py
uzpreprocessor/processor.py
uzpreprocessor/text.py
uzpreprocessor/time.py
uzpreprocessor-1.0.5.dist-info/licenses/LICENSE
uzpreprocessor-1.0.5.dist-info/METADATA
uzpreprocessor-1.0.5.dist-info/WHEEL
uzpreprocessor-1.0.5.dist-info/top_level.txt
uzpreprocessor-1.0.5.dist-info/RECORD
