Metadata-Version: 2.4
Name: uzpreprocessor
Version: 1.0.5
Summary: Uzbek text preprocessing library for converting numbers, dates, times, and currency to words
Home-page: https://github.com/jakharbek/py-uzpreprocessor
Author: Javhar Abdulatipov
Author-email: Javhar Abdulatipov <jakharbek@gmail.com>
License: MIT
Project-URL: Homepage, https://github.com/jakharbek/py-uzpreprocessor
Project-URL: Documentation, https://github.com/jakharbek/py-uzpreprocessor#readme
Project-URL: Repository, https://github.com/jakharbek/py-uzpreprocessor
Project-URL: Issues, https://github.com/jakharbek/py-uzpreprocessor/issues
Keywords: uzbek,text,preprocessing,nlp,numbers,dates,currency,words,conversion,latin
Classifier: Development Status :: 4 - Beta
Classifier: Intended Audience :: Developers
Classifier: License :: OSI Approved :: MIT License
Classifier: Programming Language :: Python :: 3
Classifier: Programming Language :: Python :: 3.8
Classifier: Programming Language :: Python :: 3.9
Classifier: Programming Language :: Python :: 3.10
Classifier: Programming Language :: Python :: 3.11
Classifier: Programming Language :: Python :: 3.12
Classifier: Topic :: Software Development :: Libraries :: Python Modules
Classifier: Topic :: Text Processing :: Linguistic
Classifier: Topic :: Utilities
Requires-Python: >=3.8
License-File: LICENSE
Provides-Extra: dev
Requires-Dist: pytest>=7.0.0; extra == "dev"
Requires-Dist: pytest-cov>=4.0.0; extra == "dev"
Requires-Dist: black>=23.0.0; extra == "dev"
Requires-Dist: mypy>=1.0.0; extra == "dev"
Requires-Dist: ruff>=0.1.0; extra == "dev"
Dynamic: author
Dynamic: home-page
Dynamic: license-file
Dynamic: requires-python
